edc_metadata/__init__.py
edc_metadata/admin_site.py
edc_metadata/apps.py
edc_metadata/auths.py
edc_metadata/choices.py
edc_metadata/constants.py
edc_metadata/managers.py
edc_metadata/metadata_handler.py
edc_metadata/metadata_inspector.py
edc_metadata/metadata_refresher.py
edc_metadata/metadata_updater.py
edc_metadata/next_form_getter.py
edc_metadata/offline_models.py
edc_metadata/stubs.py
edc_metadata/system_checks.py
edc_metadata/update_metadata_on_schedule_change.py
edc_metadata/urls.py
edc_metadata/utils.py
edc_metadata/admin/__init__.py
edc_metadata/admin/crf_metadata.py
edc_metadata/admin/list_filters.py
edc_metadata/admin/modeladmin_mixins.py
edc_metadata/admin/requisition_metadata.py
edc_metadata/management/__init__.py
edc_metadata/management/commands/__init__.py
edc_metadata/management/commands/update_metadata.py
edc_metadata/management/commands/update_metadata_schedule_names.py
edc_metadata/management/commands/validate_entry_status.py
edc_metadata/management/commands/validate_rule_groups.py
edc_metadata/metadata/__init__.py
edc_metadata/metadata/crf_metadata_getter.py
edc_metadata/metadata/metadata.py
edc_metadata/metadata/metadata_getter.py
edc_metadata/metadata/requisition_metadata_getter.py
edc_metadata/metadata_helper/__init__.py
edc_metadata/metadata_helper/metadata_helper.py
edc_metadata/metadata_helper/metadata_helper_mixin.py
edc_metadata/metadata_mixins/__init__.py
edc_metadata/metadata_mixins/source_model_metadata_mixin.py
edc_metadata/metadata_rules/__init__.py
edc_metadata/metadata_rules/decorators.py
edc_metadata/metadata_rules/logic.py
edc_metadata/metadata_rules/metadata_rule_evaluator.py
edc_metadata/metadata_rules/persistant_singleton_mixin.py
edc_metadata/metadata_rules/predicate.py
edc_metadata/metadata_rules/rule.py
edc_metadata/metadata_rules/rule_evaluator.py
edc_metadata/metadata_rules/rule_group.py
edc_metadata/metadata_rules/rule_group_meta_options.py
edc_metadata/metadata_rules/rule_group_metaclass.py
edc_metadata-1.0.5.dist-info/licenses/AUTHORS.rst
edc_metadata-1.0.5.dist-info/licenses/LICENSE
edc_metadata-1.0.5.dist-info/METADATA
edc_metadata-1.0.5.dist-info/WHEEL
edc_metadata-1.0.5.dist-info/top_level.txt
edc_metadata-1.0.5.dist-info/RECORD
